flexpass/__init__.py
flexpass/__main__.py
flexpass/_version.py
flexpass/errors.py
flexpass/utils.py
flexpass/backends/__init__.py
flexpass/backends/gpg.py
flexpass/backends/secretservice.py
flexpass/backends/wincred.py
flexpass-0.1.2.dist-info/LICENSE.txt
flexpass-0.1.2.dist-info/METADATA
flexpass-0.1.2.dist-info/WHEEL
flexpass-0.1.2.dist-info/entry_points.txt
flexpass-0.1.2.dist-info/top_level.txt
flexpass-0.1.2.dist-info/RECORD
