Metadata-Version: 2.1
Name: flexpass
Version: 0.1.2
Summary: A simple yet flexible library (and command-line application) to access passwords from various backends (GPG/pass, Linux SecretService, Windows Credentials Manager, etc).
Author-email: Ipamo <dev@ipamo.net>
Project-URL: Homepage, https://gitlab.com/ipamo/flexpass
Project-URL: Bug Tracker, https://gitlab.com/ipamo/flexpass/issues
Keywords: pass,keyring,secrets,passwords,password,manager,gpg,wallet,kwallet,kwalletmanager,keepass,keepassxc
Classifier: Development Status :: 4 - Beta
Classifier: License :: OSI Approved :: MIT License
Classifier: Operating System :: OS Independent
Classifier: Programming Language :: Python :: 3
Classifier: Programming Language :: Python :: 3.7
Classifier: Programming Language :: Python :: 3.8
Classifier: Programming Language :: Python :: 3.9
Classifier: Programming Language :: Python :: 3.10
Classifier: Programming Language :: Python :: 3.11
Classifier: Programming Language :: Python :: 3.12
Classifier: Environment :: Console
Classifier: Topic :: Security
Classifier: Topic :: Software Development :: Libraries
Requires-Python: >=3.7
License-File: LICENSE.txt
Requires-Dist: secretstorage ; sys_platform == "linux"
Requires-Dist: pywin32 ; sys_platform == "win32"
